acme_collectors/__init__.py
acme_collectors/collectors/__init__.py
acme_collectors/collectors/contents_collector.py
acme_collectors/engines/__init__.py
acme_collectors/engines/aljazeera_engine.py
acme_collectors/engines/cnn_engine.py
acme_collectors/engines/google_nlp.py
acme_collectors/engines/ibm_watson_nlp.py
acme_collectors/engines/mysql_engine.py
acme_collectors/engines/notifications.py
acme_collectors/scripts/__init__.py
acme_collectors/scripts/server_jobs.py
acme_collectors/utils/__init__.py
acme_collectors/utils/constants.py
acme_collectors/utils/helpers.py
acme_collectors/utils/pdf_parser.py
acme_collectors/utils/tone_classifiers.py
acme_collectors/utils/tools/__init__.py
tests/__init__.py
tests/unit/__init__.py
tests/unit/test_aljazeera_engine.py
tests/unit/test_cnn_engine.py
tests/unit/test_google_nlp_helper.py
tests/unit/test_label_articles.py
tests/unit/test_notification_template.py
tests/unit/test_pdf_utils.py
tests/unit/test_tone_classifier.py
tests/unit/test_watson_tone_nlp.py
acmecontentcollectors_pkg_rioatmadja2018-0.1.1618454424.dist-info/METADATA
acmecontentcollectors_pkg_rioatmadja2018-0.1.1618454424.dist-info/WHEEL
acmecontentcollectors_pkg_rioatmadja2018-0.1.1618454424.dist-info/top_level.txt
acmecontentcollectors_pkg_rioatmadja2018-0.1.1618454424.dist-info/zip-safe
acmecontentcollectors_pkg_rioatmadja2018-0.1.1618454424.dist-info/RECORD
