Metadata-Version: 2.1
Name: acmecontentcollectors-pkg-rioatmadja2018
Version: 0.1.1618454424
Summary: Python wheel to collect data about the Islamic Recruitments.
Home-page: UNKNOWN
Author: Rio Atmadja
Author-email: rioatmadja2018@gmail.com
License: UNKNOWN
Platform: UNKNOWN
Classifier: Programming Language :: Python :: 3
Classifier: Operating System :: OS Independent
Classifier: Intended Audience :: Developers
Requires-Python: >=3.6
Requires-Dist: google-api-core (==1.26.3)
Requires-Dist: google-auth (>=1.28.0)
Requires-Dist: google-auth-oauthlib (>=0.4.4)
Requires-Dist: google-cloud-core (==1.4.3)
Requires-Dist: google-cloud-storage (==1.32.0)
Requires-Dist: google-cloud-translate (==3.0.1)
Requires-Dist: google-cloud-vision (==2.0.0)
Requires-Dist: google-crc32c (==1.0.0)
Requires-Dist: google-resumable-media (==1.1.0)
Requires-Dist: googleapis-common-protos (>=1.53.0)
Requires-Dist: pandas
Requires-Dist: numpy
Requires-Dist: bs4
Requires-Dist: pymysql
Requires-Dist: ibm-watson
Requires-Dist: python-twitter
Requires-Dist: grpcio
Requires-Dist: sklearn
Requires-Dist: nltk
Requires-Dist: pdfreader
Requires-Dist: phantomjs
Requires-Dist: textblob
